<templateSet group="AndroidLog">
  <template name="ld" value="Log.d(&quot;lyn- $METHOD_NAME$&quot;, &quot;$name$:&quot; + $value$);" description="log debug" toReformat="true" toShortenFQNames="true">
    <variable name="METHOD_NAME" expression="methodName()" defaultValue="" alwaysStopAt="false" />
    <variable name="name" expression="" defaultValue="" alwaysStopAt="true" />
    <variable name="value" expression="" defaultValue="" alwaysStopAt="true" />
    <context>
      <option name="JAVA_STATEMENT" value="true" />
    </context>
  </template>
</templateSet>